app/__init__.py
dev/__init__.py
dev/det_pick/__init__.py
dev/det_pick/tfDataset.py
dev/det_pick/train.py
dev/fmp/__init__.py
dev/fmp/tfDataset.py
dev/fmp/train.py
ditingtools-0.0.1.dist-info/LICENSE
ditingtools-0.0.1.dist-info/METADATA
ditingtools-0.0.1.dist-info/WHEEL
ditingtools-0.0.1.dist-info/top_level.txt
ditingtools-0.0.1.dist-info/RECORD
