Metadata-Version: 2.1
Name: ditingtools
Version: 0.0.1
Summary: ditingtools_0.0.1_upload_test
Author: Xiao Zhuowei & Zhao Ming
Author-email: xiaozhuowei@mail.iggcas.ac.cn
Classifier: Programming Language :: Python :: 3
Classifier: License :: OSI Approved :: MIT License
Classifier: Operating System :: OS Independent
Requires-Python: >=3.6
License-File: LICENSE
